pyssc32-0.4.2.data/scripts/ssc32yaml.py
pyssc32-0.4.2.dist-info/DESCRIPTION.rst
pyssc32-0.4.2.dist-info/METADATA
pyssc32-0.4.2.dist-info/RECORD
pyssc32-0.4.2.dist-info/WHEEL
pyssc32-0.4.2.dist-info/metadata.json
pyssc32-0.4.2.dist-info/top_level.txt
ssc32/__init__.py
ssc32/script.py
ssc32/ssc32.py
