Metadata-Version: 2.0
Name: pyssc32
Version: 0.4.2
Summary: SSC32 controlling library
Home-page: https://bitbucket.org/vooon/pyssc32/
Author: Vladimir Ermakov
Author-email: vooon341@gmail.com
License: MIT
Download-URL: https://bitbucket.org/vooon/pyssc32/get/0.4.2.tar.gz
Keywords: SSC32,Robotics,library
Platform: any
Classifier: Development Status :: 4 - Beta
Classifier: License :: OSI Approved :: MIT License
Classifier: Operating System :: OS Independent
Classifier: Programming Language :: Python
Classifier: Intended Audience :: Developers
Requires-Dist: pyserial
Requires-Dist: pyyaml
